uci_net/__init__.py
uci_net/engine.py
uci_net/tcp_client.py
uci_net/tcp_server.py
uci_net/tcp_server_on_wine.py
uci_net/uci_driver.py
uci_net/uci_driver_over_tcp.py
uci_net/samples/driver.py
uci_net-1.2.7.dist-info/LICENCE
uci_net-1.2.7.dist-info/METADATA
uci_net-1.2.7.dist-info/WHEEL
uci_net-1.2.7.dist-info/top_level.txt
uci_net-1.2.7.dist-info/RECORD
