Metadata-Version: 2.1
Name: uci-net
Version: 1.2.7
Summary: Universal Chess Interface client-server conversation.
Author-email: Roger Marsh <roger.marsh@solentware.co.uk>
License: Licence for pydbitkit package
Project-URL: Homepage, http://www.solentware.co.uk
Project-URL: Repository, https://github.com/RogerMarsh/uci-net.git
Project-URL: Bug Tracker, https://github.com/RogerMarsh/uci-net/issues
Classifier: License :: OSI Approved :: BSD License
Classifier: Programming Language :: Python :: 3.7
Classifier: Programming Language :: Python :: 3.8
Classifier: Programming Language :: Python :: 3.9
Classifier: Programming Language :: Python :: 3.10
Classifier: Programming Language :: Python :: 3.11
Classifier: Operating System :: OS Independent
Classifier: Topic :: Software Development
Classifier: Intended Audience :: Developers
Classifier: Development Status :: 3 - Alpha
License-File: LICENCE
